LICENSE.txt
MANIFEST.in
README.md
RELIC-INFO
setup.py
firewatch/__init__.py
firewatch/firewatch.py
firewatch/version.py
firewatch.egg-info/PKG-INFO
firewatch.egg-info/SOURCES.txt
firewatch.egg-info/dependency_links.txt
firewatch.egg-info/entry_points.txt
firewatch.egg-info/requires.txt
firewatch.egg-info/top_level.txt