Metadata-Version: 2.1
Name: firewatch
Version: 0.0.4
Summary: A utility to display the timeline of a Conda channel
Home-page: https://github.com/astroconda/firewatch
Author: Joseph Hunkeler
Author-email: jhunk@stsci.edu
License: BSD
Classifier: Intended Audience :: System Administrators
Classifier: License :: OSI Approved :: BSD License
Classifier: Operating System :: OS Independent
Classifier: Environment :: Console
Classifier: Programming Language :: Python :: 3 :: Only
Classifier: Programming Language :: Python :: 3.6
Classifier: Topic :: Utilities
Classifier: Topic :: Software Development :: Libraries :: Python Modules
License-File: LICENSE.txt
